pyCustomer/__init__.py
pyCustomer/customerOA_Save.py
pyCustomer/customerSave.py
pyCustomer/myMath.py
pyrdt/__init__.py
pyrdt/atom.py
pyrdt/combo.py
pyrdt/math.py
pyrdt/stat.py
pywfz/__init__.py
pywfz/myMath.py
pywfz/sql.py
pywfz/util.py
pyCustomer-1.0.2.dist-info/LICENSE
pyCustomer-1.0.2.dist-info/METADATA
pyCustomer-1.0.2.dist-info/WHEEL
pyCustomer-1.0.2.dist-info/top_level.txt
pyCustomer-1.0.2.dist-info/RECORD
