Metadata-Version: 2.1
Name: pyCustomer
Version: 1.0.2
Summary: reshape data type in py language 
Home-page: http://www.reshapedata.com
Author: hulilei
Author-email: hulilei@takewiki.com.cn
License: Apache License
Keywords: reshapedata,rdt,pyrdt
Requires-Python: >=3.6
License-File: LICENSE
Requires-Dist: requests
